[
    { 
        "name": "Crema fría de espárragos",
        "ingredients": ["Espárragos de bote", "Huevo duro", "Mahonesa"],
        "steps": [ 
            "Mezclar todos los ingredientes con la batidora.",
            "Añadir agua del bote de esparrágos para darle la textura adecuada."
        ],
        "tags": ["sopa", "frío"]
    },
    {
        "name": "Gazpacho",
        "ingredients": ["Pan", "Ajo", "Cebolla", "Pimiento verde", "Pepino", "Tomate", "Aceite" ],
        "steps": [
            "Pon el pan en agua.",
            "Mezcla todos los ingredientes con la batidora",
            "Pon en la nevera para que se enfríe"
        ],
        "tags": ["sopa", "frío"]
    },
    {
        "name": "Avena de toda la noche",
        "ingredients": ["Avena", "Leche", "Pasas", "Chía" ],
        "steps": [
            "Mezclar leche y avena hasta que quede espeso.",
            "Opcionalmente incluir pasas o chía.",
            "Dejar toda la noche en la nevera para que se hidrate la avena",
            "Se puede usar yogurt en lugar de leche",
            "Acompañar con nueces, chocolate, fruta cortada, ..."
        ],
        "tags": ["Desayuno"]
    },
    {
        "name": "",
        "ingredients": ["", "" ],
        "steps": [
            "",
            ""
        ],
        "tags": [""]
    },
    {
        "name": "",
        "ingredients": ["", "" ],
        "steps": [
            "",
            ""
        ],
        "tags": [""]
    }
]
